gradio_agentvisualizer/__init__.py
gradio_agentvisualizer/agentvisualizer.py
gradio_agentvisualizer/agentvisualizer.pyi
gradio_agentvisualizer/utils.py
gradio_agentvisualizer/templates/component/index.js
gradio_agentvisualizer/templates/component/style.css
gradio_agentvisualizer/templates/example/index.js
gradio_agentvisualizer/templates/example/style.css
gradio_agentvisualizer-0.0.3.dist-info/METADATA
gradio_agentvisualizer-0.0.3.dist-info/WHEEL
gradio_agentvisualizer-0.0.3.dist-info/RECORD
