Metadata-Version: 2.4
Name: gradio_agentvisualizer
Version: 0.0.3
Summary: Python library for easily interacting with trained machine learning models
Author-email: Thadeus Zambellis <thaddeus.zambellis@gmail.com>
License-Expression: Apache-2.0
Keywords: gradio-custom-component,gradio-template-HTML
Classifier: Development Status :: 3 - Alpha
Classifier: Operating System :: OS Independent
Classifier: Programming Language :: Python :: 3
Classifier: Programming Language :: Python :: 3 :: Only
Classifier: Programming Language :: Python :: 3.8
Classifier: Programming Language :: Python :: 3.9
Classifier: Programming Language :: Python :: 3.10
Classifier: Programming Language :: Python :: 3.11
Classifier: Topic :: Scientific/Engineering
Classifier: Topic :: Scientific/Engineering :: Artificial Intelligence
Classifier: Topic :: Scientific/Engineering :: Visualization
Requires-Python: >=3.8
Requires-Dist: gradio<6.0,>=4.0
Requires-Dist: mcp
Requires-Dist: smolagents[mcp]
Provides-Extra: dev
Requires-Dist: build; extra == 'dev'
Requires-Dist: twine; extra == 'dev'
